fasttracks/dataio.py
fasttracks/likelihood.py
fasttracks/tracks.py
fasttracks-0.1.0.dist-info/LICENSE.md
fasttracks-0.1.0.dist-info/METADATA
fasttracks-0.1.0.dist-info/WHEEL
fasttracks-0.1.0.dist-info/top_level.txt
fasttracks-0.1.0.dist-info/RECORD
