Metadata-Version: 2.2
Name: fasttracks
Version: 0.1.0
Summary: A massively-parallel engine for generic CW detection statistics.
Author-email: Rodrigo Tenorio <rodrigo.tenorio.marquez@gmail.com>
License: MIT License
Project-URL: Homepage, https://github.com/Rodrigo-Tenorio/fasttracks
Project-URL: Issues, https://github.com/Rodrigo-Tenorio/fasttracks/issues
Classifier: Programming Language :: Python :: 3
Classifier: License :: OSI Approved :: MIT License
Classifier: Topic :: Scientific/Engineering :: Astronomy
Classifier: Topic :: Scientific/Engineering :: Physics
Requires-Python: >=3.10
License-File: LICENSE.md
Requires-Dist: cows3
Requires-Dist: jax
Requires-Dist: lalsuite
Requires-Dist: numpy
Requires-Dist: pyfstat
Provides-Extra: dev
Requires-Dist: black; extra == "dev"
Requires-Dist: flake8; extra == "dev"
Requires-Dist: pytest; extra == "dev"
